[
  {
    "date": "2013-11-29", 
    "results": {
      "blake": false, 
      "michaellake": false, 
      "jossay": false, 
      "gregg": false, 
      "christy": false, 
      "tobias": false, 
      "kathryn": false, 
      "tyler": false, 
      "derek": false, 
      "jonnye": false, 
      "tom": false, 
      "blakeware": false, 
      "woody": false, 
      "tes": false, 
      "nate": false
    }
  }, 
  {
    "date": "2013-12-06", 
    "results": {
      "trung": false, 
      "alex": false, 
      "michaellake": false, 
      "jossay": false, 
      "gregg": false, 
      "mattyohe": false, 
      "jeffpamer": false, 
      "kathryn": false, 
      "tom": false, 
      "tyler": false, 
      "derek": false, 
      "jonnye": false, 
      "christy": false, 
      "kylebye": false, 
      "woody": false, 
      "tes": false, 
      "kevin": true, 
      "jesseprehodick": false
    }
  }, 
  {
    "date": "2013-12-13", 
    "results": {
      "tom": false, 
      "gregg": false, 
      "mattyohe": false, 
      "tobias": false, 
      "matthewes": false, 
      "mikemoore": false, 
      "mikewilkerson": false, 
      "derek": false, 
      "jossay": true, 
      "woody": false, 
      "kayla": false, 
      "jeffpamer": false, 
      "dayne": false, 
      "michaelrecachinas": false, 
      "kevin": false, 
      "jesseprehodick": true
    }
  }, 
  {
    "date": "2013-12-20", 
    "results": {
      "alex": false, 
      "woody": false, 
      "jossay": false, 
      "mattyohe": false, 
      "derek": false, 
      "jonnye": false, 
      "christy": false, 
      "michaelprichard": false, 
      "trung": false, 
      "eric": true, 
      "kevin": false, 
      "sean": false
    }
  }, 
  {
    "date": "2014-01-10", 
    "results": {
      "rob": false, 
      "christy": false, 
      "jeffpamer": false, 
      "kathryn": false, 
      "woody": false, 
      "eric": false, 
      "kevin": false, 
      "michaellake": false, 
      "robert": false, 
      "brandon": false, 
      "tyler": false, 
      "derek": false, 
      "cassie": false, 
      "tom": false, 
      "michaelprichard": false, 
      "dayne": false, 
      "monica": false, 
      "christian": false, 
      "gregg": false, 
      "max": false, 
      "tobias": false, 
      "jossay": false, 
      "trung": false, 
      "patrick": false, 
      "andrewcarter": false, 
      "matthewes": false, 
      "jesseprehodick": false, 
      "alex": false, 
      "jeffkusi": false, 
      "tes": false
    }
  }
]
